drkv_ec2_utils/__init__.py
drkv_ec2_utils/ec2_utils.py
drkv_ec2_utils-1.10.dist-info/METADATA
drkv_ec2_utils-1.10.dist-info/WHEEL
drkv_ec2_utils-1.10.dist-info/top_level.txt
drkv_ec2_utils-1.10.dist-info/RECORD
